billy_client/api.py
billy_client/__init__.py
billy_client/tests/test_against_server.py
billy_client/tests/test_api.py
billy_client/tests/__init__.py
billy_client-0.0.5.dist-info/DESCRIPTION.rst
billy_client-0.0.5.dist-info/METADATA
billy_client-0.0.5.dist-info/pydist.json
billy_client-0.0.5.dist-info/RECORD
billy_client-0.0.5.dist-info/top_level.txt
billy_client-0.0.5.dist-info/WHEEL
