Metadata-Version: 2.0
Name: billy-client
Version: 0.0.5
Summary: Recurring payment system client library
Home-page: https://github.com/victorlin/billy-client
Author: Balanced Payment
Author-email: support@balancedpayments.com
License: UNKNOWN
Keywords: billy payment recurring schedule client
Platform: UNKNOWN
Classifier: Programming Language :: Python
Requires-Dist: requests
